Metadata-Version: 2.1
Name: nz-stream-depletion
Version: 0.0.0
Summary: Functions to calculate stream depletion using analytical solutions
Home-page: https://github.com/mullenkamp/nz-stream-depletion
Author: Mike Kittridge
Author-email: mullenkamp1@gmail.com
License: Apache
Keywords: nz groundwater depletion
Platform: UNKNOWN
Classifier: Development Status :: 3 - Alpha
Classifier: Intended Audience :: Developers
Classifier: Topic :: Software Development :: Build Tools
Classifier: License :: OSI Approved :: Apache Software License
Classifier: Programming Language :: Python :: 3.8
Classifier: Programming Language :: Python :: 3.9
License-File: LICENSE
